ascript/__init__.py
ascript/android/__init__.py
ascript/android/action.py
ascript/android/data.py
ascript/android/media.py
ascript/android/node.py
ascript/android/plug.py
ascript/android/screen.py
ascript/android/system.py
ascript/android/ui.py
ascript/android/action/__init__.py
ascript/android/action/ashid.py
ascript/android/screen/__init__.py
ascript/android/screen/ascv.py
ascript/android/screen/color_tools.py
ascript/android/screen/gp.py
ascript/android/screen/gp_tasks.py
ascript/android/screen/gp_tool.py
ascript/android/shizuku/__init__.py
ascript/android/system/__init__.py
ascript/ios/__init__.py
ascript/ios/action.py
ascript/ios/ime.py
ascript/ios/media.py
ascript/ios/node.py
ascript/ios/ui.py
ascript/ios/action/__init__.py
ascript/ios/developer/__init__.py
ascript/ios/developer/ws.py
ascript/ios/developer/api/__init__.py
ascript/ios/developer/api/api_2_android.py
ascript/ios/developer/api/api_code.py
ascript/ios/developer/api/api_file.py
ascript/ios/developer/api/api_label.py
ascript/ios/developer/api/api_module.py
ascript/ios/developer/api/api_node.py
ascript/ios/developer/api/api_screen.py
ascript/ios/developer/api/api_tool.py
ascript/ios/developer/api/dao.py
ascript/ios/developer/api/data.py
ascript/ios/developer/api/file_utils.py
ascript/ios/developer/api/label_utils.py
ascript/ios/developer/api/line_helper.py
ascript/ios/developer/api/oc.py
ascript/ios/developer/api/oc_gp.py
ascript/ios/developer/api/sp_utils.py
ascript/ios/developer/api/utils.py
ascript/ios/developer/api/wda_gp.py
ascript/ios/ios/__init__.py
ascript/ios/ios/ime.py
ascript/ios/ios/media.py
ascript/ios/ios/node.py
ascript/ios/ios/ui.py
ascript/ios/ios/action/__init__.py
ascript/ios/ios/developer/__init__.py
ascript/ios/ios/developer/ws.py
ascript/ios/ios/developer/api/__init__.py
ascript/ios/ios/developer/api/api_2_android.py
ascript/ios/ios/developer/api/api_code.py
ascript/ios/ios/developer/api/api_file.py
ascript/ios/ios/developer/api/api_label.py
ascript_tip-0.0.3.61.dist-info/METADATA
ascript_tip-0.0.3.61.dist-info/WHEEL
ascript_tip-0.0.3.61.dist-info/top_level.txt
ascript_tip-0.0.3.61.dist-info/RECORD
