Metadata-Version: 2.1
Name: ascript-tip
Version: 0.0.3.61
Summary: ascript Python库
Home-page: https://ascript.cn/
Author: aojoy
Author-email: aojoytec@163.com
License: MIT
Keywords: python,ascript
Classifier: Programming Language :: Python :: 3
Classifier: License :: OSI Approved :: MIT License
Classifier: Operating System :: OS Independent
